[
  {
    "pk": 1,
	"model": "accounts.twitterthread",
	"fields": {
		"account": 1,
		"tweet_id": 123456,
		"conversation_id": "abc123",
		"conversation": "This is the first conversation.",
		"created_at": "2022-01-01T00:00:00Z"
	}
  },
  {
    "pk": 2,
	"model": "accounts.twitterthread",
	"fields": {
		"account": 1,
		"tweet_id": 234567,
		"conversation_id": "def456",
		"conversation": "This is the second conversation.",
		"created_at": "2022-01-02T00:00:00Z"
	}
  },
  {
    "pk": 3,
	"model": "accounts.twitterthread",
	"fields": {
		"account": 1,
		"tweet_id": 345678,
		"conversation_id": "ghi789",
		"conversation": "This is the third conversation.",
		"created_at": "2022-01-03T00:00:00Z"
	}
  },
  {
    "pk": 4,
	"model": "accounts.twitterthread",
	"fields": {
		"account": 2,
		"tweet_id": 456789,
		"conversation_id": "jkl012",
		"conversation": "This is the fourth conversation.",
		"created_at": "2022-01-04T00:00:00Z"
	}
  },
  {
    "pk": 5,
	"model": "accounts.twitterthread",
	"fields": {
		"account": 2,
		"tweet_id": 567890,
		"conversation_id": "mno345",
		"conversation": "This is the fifth conversation.",
		"created_at": "2022-01-05T00:00:00Z"
	}
  },
  {
    "pk": 6,
	"model": "accounts.twitterthread",
	"fields": {
		"account": 2,
		"tweet_id": 678901,
		"conversation_id": "pqr678",
		"conversation": "This is the sixth conversation.",
		"created_at": "2022-01-06T00:00:00Z"
	}
  },
  {
    "pk": 7,
	"model": "accounts.twitterthread",
	"fields": {
		"account": 3,
		"tweet_id": 789012,
		"conversation_id": "stu901",
		"conversation": "This is the seventh conversation.",
		"created_at": "2022-01-07T00:00:00Z"
	}
  },
  {
    "pk": 8,
	"model": "accounts.twitterthread",
	"fields": {
		"account": 3,
		"tweet_id": 890123,
		"conversation_id": "vwx234",
		"conversation": "This is the eighth conversation.",
		"created_at": "2022-01-08T00:00:00Z"
	}
  },
  {
    "pk": 9,
	"model": "accounts.twitterthread",
	"fields": {
		"account": 3,
		"tweet_id": 901234,
		"conversation_id": "yza567",
		"conversation": "This is the ninth conversation.",
		"created_at": "2022-01-09T00:00:00Z"
	}
  },
  {
    "pk": 10,
	"model": "accounts.twitterthread",
 	"fields": {
		"account": 3,
		"tweet_id": 123456,
		"conversation_id": "bcd890",
		"conversation": "This is the tenth conversation.",
		"created_at": "2022-01-10T00:00:00Z"
	}
  }
]
